byteflow-0.2.1a7.post4.dist-info/METADATA
byteflow-0.2.1a7.post4.dist-info/WHEEL
byteflow/__init__.py
byteflow/contentio/__init__.py
byteflow/contentio/common.py
byteflow/contentio/contentio.py
byteflow/contentio/helpers.py
byteflow/core/__init__.py
byteflow/core/core.py
byteflow/data_collectors/__init__.py
byteflow/data_collectors/api.py
byteflow/data_collectors/base.py
byteflow/data_collectors/common.py
byteflow/entrypoint.py
byteflow/exceptions/__init__.py
byteflow/exceptions/exceptions.py
byteflow/py.typed
byteflow/resources/__init__.py
byteflow/resources/api.py
byteflow/resources/base.py
byteflow/scheduling/__init__.py
byteflow/scheduling/base.py
byteflow/scheduling/limits.py
byteflow/scheduling/timeinterval.py
byteflow/scheduling/triggers.py
byteflow/storages/__init__.py
byteflow/storages/base.py
byteflow/storages/blob.py
byteflow/utils/__init__.py
byteflow/utils/misc.py
byteflow-0.2.1a7.post4.dist-info/RECORD
