Metadata-Version: 2.1
Name: byteflow
Version: 0.2.1a7.post4
Summary: Simple scrape as SELECT * FROM ANYTHING in network
Keywords: scraping,web scraping,asyncio,web crawler,api crawler,api scraping
Author-Email: Danchuk Ivan <ivan.s.danchuk@gmail.com>
Maintainer-Email: Danchuk Ivan <ivan.s.danchuk@gmail.com>
License: Apache 2.0
Classifier: Development Status :: 3 - Alpha
Classifier: License :: OSI Approved :: Apache Software License
Classifier: Operating System :: Microsoft
Classifier: Operating System :: POSIX
Classifier: Programming Language :: Python :: 3 :: Only
Classifier: Topic :: Software Development :: Libraries
Project-URL: Documentation, https://danchukivan.github.io/byteflow/
Project-URL: Repository, https://github.com/DanchukIvan/byteflow.git
Requires-Python: >=3.11
Requires-Dist: aiohttp<4.0.0,>=3.8
Requires-Dist: aioitertools<1.0.0,>=0.11.0
Requires-Dist: asyncio
Requires-Dist: fsspec<2024.0.0,>=2023.12.2
Requires-Dist: more-itertools
Requires-Dist: regex<2024.0.0,>=2023.12.25
Requires-Dist: uvloop; platform_system == "Linux"
Requires-Dist: yarl<2.0.0,>=1.9.4
Requires-Dist: dateparser>=1.2.0
Requires-Dist: loguru>=0.7.2; extra == "log"
Requires-Dist: loguru-config>=0.1.0; extra == "log"
Provides-Extra: log
